<?xml version="1.0" encoding="UTF-8" ?>
<Library name="sap.ui.table" xmlns="http://www.sap.com/ui5/ide/templates/xmlview">
<Template name="sap.ui.table.AnalyticalColumn" alias="AnalyticalColumn,Column">
	<jsTemplate><![CDATA[new sap.ui.table.AnalyticalColumn({
	id: "${id}", // sap.ui.core.ID
	width: undefined, // sap.ui.core.CSSSize
	minWidth: 0, // int, since 1.44.1
	flexible: true, // boolean
	resizable: true, // boolean
	hAlign: sap.ui.core.HorizontalAlign.Begin, // sap.ui.core.HorizontalAlign
	sorted: false, // boolean
	sortOrder: sap.ui.table.SortOrder.Ascending, // sap.ui.table.SortOrder
	sortProperty: undefined, // string
	filtered: false, // boolean
	filterProperty: undefined, // string
	filterValue: undefined, // string
	filterOperator: undefined, // string
	defaultFilterOperator: undefined, // string
	filterType: undefined, // any, since 1.9.2
	grouped: false, // boolean
	visible: true, // boolean
	name: undefined, // string, since 1.11.1
	showFilterMenuEntry: true, // boolean, since 1.13.0
	showSortMenuEntry: true, // boolean, since 1.13.0
	headerSpan: 1, // any
	autoResizable: false, // boolean, since 1.21.1
	leadingProperty: undefined, // string
	summed: false, // boolean
	inResult: false, // boolean
	showIfGrouped: false, // boolean
	groupHeaderFormatter: undefined, // any
	tooltip: undefined, // sap.ui.core.TooltipBase
	customData: [], // sap.ui.core.CustomData
	dependents: [], // sap.ui.core.Element, since 1.19
	label: undefined, // sap.ui.core.Control
	multiLabels: [], // sap.ui.core.Control, since 1.13.1
	template: undefined, // sap.ui.core.Control
	menu: undefined, // sap.ui.unified.Menu
	columnMenuOpen: [function (oEvent) {
		var ${control} = oEvent.getSource();
	}, this] // since 1.33.0
})
]]></jsTemplate>
	<xmlTemplate><![CDATA[<AnalyticalColumn xmlns="sap.ui.table"
	id="${id}"
	width=""
	minWidth="0"
	flexible="true"
	resizable="true"
	hAlign="Begin"
	sorted="false"
	sortOrder="Ascending"
	sortProperty=""
	filtered="false"
	filterProperty=""
	filterValue=""
	filterOperator=""
	defaultFilterOperator=""
	filterType=""
	grouped="false"
	visible="true"
	name=""
	showFilterMenuEntry="true"
	showSortMenuEntry="true"
	headerSpan="1"
	autoResizable="false"
	leadingProperty=""
	summed="false"
	inResult="false"
	showIfGrouped="false"
	groupHeaderFormatter=""
	columnMenuOpen="">
		<tooltip></tooltip> <!-- sap.ui.core.TooltipBase -->
		<dependents></dependents> <!-- sap.ui.core.Element, since 1.19 -->
		<label></label> <!-- sap.ui.core.Control -->
		<multiLabels></multiLabels> <!-- sap.ui.core.Control, since 1.13.1 -->
		<template></template> <!-- sap.ui.core.Control -->
		<menu></menu> <!-- sap.ui.unified.Menu -->
</AnalyticalColumn>
]]></xmlTemplate>
</Template>
<Template name="sap.ui.table.AnalyticalColumnMenu" alias="AnalyticalColumnMenu,Menu">
	<jsTemplate><![CDATA[new sap.ui.table.AnalyticalColumnMenu({
	id: "${id}", // sap.ui.core.ID
	busy: false, // boolean
	busyIndicatorDelay: 1000, // int
	visible: true, // boolean
	fieldGroupIds: [], // string[], since 1.31
	enabled: true, // boolean
	ariaDescription: undefined, // string
	maxVisibleItems: 0, // int
	pageSize: 5, // int, since 1.25.0
	tooltip: undefined, // sap.ui.core.TooltipBase
	customData: [], // sap.ui.core.CustomData
	dependents: [], // sap.ui.core.Element, since 1.19
	items: [], // sap.ui.unified.MenuItemBase
	ariaLabelledBy: [], // sap.ui.core.Control, since 1.26.3
	validateFieldGroup: [function (oEvent) {
		var ${control} = oEvent.getSource();
	}, this],
	itemSelect: [function (oEvent) {
		var ${control} = oEvent.getSource();
	}, this]
})
]]></jsTemplate>
	<xmlTemplate><![CDATA[<AnalyticalColumnMenu xmlns="sap.ui.table"
	id="${id}"
	busy="false"
	busyIndicatorDelay="1000"
	visible="true"
	fieldGroupIds=""
	enabled="true"
	ariaDescription=""
	maxVisibleItems="0"
	pageSize="5"
	ariaLabelledBy=""
	validateFieldGroup=""
	itemSelect="">
		<tooltip></tooltip> <!-- sap.ui.core.TooltipBase -->
		<dependents></dependents> <!-- sap.ui.core.Element, since 1.19 -->
		<items></items> <!-- sap.ui.unified.MenuItemBase -->
</AnalyticalColumnMenu>
]]></xmlTemplate>
</Template>
<Template name="sap.ui.table.AnalyticalTable" alias="AnalyticalTable,Table">
	<jsTemplate><![CDATA[new sap.ui.table.AnalyticalTable({
	id: "${id}", // sap.ui.core.ID
	busy: false, // boolean
	busyIndicatorDelay: 1000, // int
	visible: true, // boolean
	fieldGroupIds: [], // string[], since 1.31
	width: "auto", // sap.ui.core.CSSSize
	rowHeight: undefined, // int
	columnHeaderHeight: undefined, // int
	columnHeaderVisible: true, // boolean
	visibleRowCount: 10, // int
	firstVisibleRow: 0, // int
	selectionMode: sap.ui.table.SelectionMode.MultiToggle, // sap.ui.table.SelectionMode
	selectionBehavior: sap.ui.table.SelectionBehavior.RowSelector, // sap.ui.table.SelectionBehavior
	selectedIndex: -1, // int
	editable: true, // boolean
	navigationMode: sap.ui.table.NavigationMode.Scrollbar, // sap.ui.table.NavigationMode
	threshold: 100, // int
	enableColumnReordering: true, // boolean
	enableGrouping: false, // boolean
	showColumnVisibilityMenu: false, // boolean
	showNoData: true, // boolean
	visibleRowCountMode: sap.ui.table.VisibleRowCountMode.Fixed, // sap.ui.table.VisibleRowCountMode, since 1.9.2
	minAutoRowCount: 5, // int
	fixedColumnCount: 0, // int
	fixedRowCount: 0, // int
	fixedBottomRowCount: 0, // int, since 1.18.7
	enableColumnFreeze: false, // boolean, since 1.21.0
	enableCellFilter: false, // boolean, since 1.21.0
	showOverlay: false, // boolean, since 1.21.2
	enableSelectAll: true, // boolean, since 1.23.0
	enableCustomFilter: false, // boolean, since 1.23.0
	enableBusyIndicator: false, // boolean, since 1.27.0
	rowActionCount: 0, // int, since 1.45.0
	sumOnTop: false, // boolean
	numberOfExpandedLevels: 0, // int
	autoExpandMode: "Bundled", // string
	columnVisibilityMenuSorter: undefined, // any
	collapseRecursive: true, // boolean
	dirty: undefined, // boolean
	tooltip: undefined, // sap.ui.core.TooltipBase
	customData: [], // sap.ui.core.CustomData
	dependents: [], // sap.ui.core.Element, since 1.19
	title: undefined, // sap.ui.core.Control
	footer: undefined, // sap.ui.core.Control
	toolbar: undefined, // sap.ui.core.Toolbar
	extension: [], // sap.ui.core.Control
	columns: [], // sap.ui.table.Column
	rows: [], // sap.ui.table.Row
	noData: undefined, // sap.ui.core.Control
	rowActionTemplate: undefined, // sap.ui.table.RowAction
	groupBy: undefined, // sap.ui.table.Column
	ariaLabelledBy: [], // sap.ui.core.Control
	validateFieldGroup: [function (oEvent) {
		var ${control} = oEvent.getSource();
	}, this],
	rowSelectionChange: [function (oEvent) {
		var ${control} = oEvent.getSource();
	}, this],
	columnSelect: [function (oEvent) {
		var ${control} = oEvent.getSource();
	}, this],
	columnResize: [function (oEvent) {
		var ${control} = oEvent.getSource();
	}, this],
	columnMove: [function (oEvent) {
		var ${control} = oEvent.getSource();
	}, this],
	sort: [function (oEvent) {
		var ${control} = oEvent.getSource();
	}, this],
	filter: [function (oEvent) {
		var ${control} = oEvent.getSource();
	}, this],
	group: [function (oEvent) {
		var ${control} = oEvent.getSource();
	}, this],
	columnVisibility: [function (oEvent) {
		var ${control} = oEvent.getSource();
	}, this],
	cellClick: [function (oEvent) {
		var ${control} = oEvent.getSource();
	}, this], // since 1.21.0
	cellContextmenu: [function (oEvent) {
		var ${control} = oEvent.getSource();
	}, this], // since 1.21.0
	columnFreeze: [function (oEvent) {
		var ${control} = oEvent.getSource();
	}, this], // since 1.21.0
	customFilter: [function (oEvent) {
		var ${control} = oEvent.getSource();
	}, this], // since 1.23.0
	firstVisibleRowChanged: [function (oEvent) {
		var ${control} = oEvent.getSource();
	}, this], // since 1.37.0
	busyStateChanged: [function (oEvent) {
		var ${control} = oEvent.getSource();
	}, this] // since 1.37.0
})
]]></jsTemplate>
	<xmlTemplate><![CDATA[<AnalyticalTable xmlns="sap.ui.table"
	id="${id}"
	busy="false"
	busyIndicatorDelay="1000"
	visible="true"
	fieldGroupIds=""
	width="auto"
	rowHeight=""
	columnHeaderHeight=""
	columnHeaderVisible="true"
	visibleRowCount="10"
	firstVisibleRow="0"
	selectionMode="MultiToggle"
	selectionBehavior="RowSelector"
	selectedIndex="-1"
	editable="true"
	navigationMode="Scrollbar"
	threshold="100"
	enableColumnReordering="true"
	enableGrouping="false"
	showColumnVisibilityMenu="false"
	showNoData="true"
	visibleRowCountMode="Fixed"
	minAutoRowCount="5"
	fixedColumnCount="0"
	fixedRowCount="0"
	fixedBottomRowCount="0"
	enableColumnFreeze="false"
	enableCellFilter="false"
	showOverlay="false"
	enableSelectAll="true"
	enableCustomFilter="false"
	enableBusyIndicator="false"
	rowActionCount="0"
	sumOnTop="false"
	numberOfExpandedLevels="0"
	autoExpandMode="Bundled"
	columnVisibilityMenuSorter=""
	collapseRecursive="true"
	dirty=""
	groupBy=""
	ariaLabelledBy=""
	validateFieldGroup=""
	rowSelectionChange=""
	columnSelect=""
	columnResize=""
	columnMove=""
	sort=""
	filter=""
	group=""
	columnVisibility=""
	cellClick=""
	cellContextmenu=""
	columnFreeze=""
	customFilter=""
	firstVisibleRowChanged=""
	busyStateChanged="">
		<tooltip></tooltip> <!-- sap.ui.core.TooltipBase -->
		<dependents></dependents> <!-- sap.ui.core.Element, since 1.19 -->
		<title></title> <!-- sap.ui.core.Control -->
		<footer></footer> <!-- sap.ui.core.Control -->
		<toolbar></toolbar> <!-- sap.ui.core.Toolbar -->
		<extension></extension> <!-- sap.ui.core.Control -->
		<columns></columns> <!-- sap.ui.table.Column -->
		<rows></rows> <!-- sap.ui.table.Row -->
		<noData></noData> <!-- sap.ui.core.Control -->
		<rowActionTemplate></rowActionTemplate> <!-- sap.ui.table.RowAction -->
</AnalyticalTable>
]]></xmlTemplate>
</Template>
<Template name="sap.ui.table.Column" alias="Column">
	<jsTemplate><![CDATA[new sap.ui.table.Column({
	id: "${id}", // sap.ui.core.ID
	width: undefined, // sap.ui.core.CSSSize
	minWidth: 0, // int, since 1.44.1
	flexible: true, // boolean
	resizable: true, // boolean
	hAlign: sap.ui.core.HorizontalAlign.Begin, // sap.ui.core.HorizontalAlign
	sorted: false, // boolean
	sortOrder: sap.ui.table.SortOrder.Ascending, // sap.ui.table.SortOrder
	sortProperty: undefined, // string
	filtered: false, // boolean
	filterProperty: undefined, // string
	filterValue: undefined, // string
	filterOperator: undefined, // string
	defaultFilterOperator: undefined, // string
	filterType: undefined, // any, since 1.9.2
	grouped: false, // boolean
	visible: true, // boolean
	name: undefined, // string, since 1.11.1
	showFilterMenuEntry: true, // boolean, since 1.13.0
	showSortMenuEntry: true, // boolean, since 1.13.0
	headerSpan: 1, // any
	autoResizable: false, // boolean, since 1.21.1
	tooltip: undefined, // sap.ui.core.TooltipBase
	customData: [], // sap.ui.core.CustomData
	dependents: [], // sap.ui.core.Element, since 1.19
	label: undefined, // sap.ui.core.Control
	multiLabels: [], // sap.ui.core.Control, since 1.13.1
	template: undefined, // sap.ui.core.Control
	menu: undefined, // sap.ui.unified.Menu
	columnMenuOpen: [function (oEvent) {
		var ${control} = oEvent.getSource();
	}, this] // since 1.33.0
})
]]></jsTemplate>
	<xmlTemplate><![CDATA[<Column xmlns="sap.ui.table"
	id="${id}"
	width=""
	minWidth="0"
	flexible="true"
	resizable="true"
	hAlign="Begin"
	sorted="false"
	sortOrder="Ascending"
	sortProperty=""
	filtered="false"
	filterProperty=""
	filterValue=""
	filterOperator=""
	defaultFilterOperator=""
	filterType=""
	grouped="false"
	visible="true"
	name=""
	showFilterMenuEntry="true"
	showSortMenuEntry="true"
	headerSpan="1"
	autoResizable="false"
	columnMenuOpen="">
		<tooltip></tooltip> <!-- sap.ui.core.TooltipBase -->
		<dependents></dependents> <!-- sap.ui.core.Element, since 1.19 -->
		<label></label> <!-- sap.ui.core.Control -->
		<multiLabels></multiLabels> <!-- sap.ui.core.Control, since 1.13.1 -->
		<template></template> <!-- sap.ui.core.Control -->
		<menu></menu> <!-- sap.ui.unified.Menu -->
</Column>
]]></xmlTemplate>
</Template>
<Template name="sap.ui.table.ColumnMenu" alias="ColumnMenu,Menu">
	<jsTemplate><![CDATA[new sap.ui.table.ColumnMenu({
	id: "${id}", // sap.ui.core.ID
	busy: false, // boolean
	busyIndicatorDelay: 1000, // int
	visible: true, // boolean
	fieldGroupIds: [], // string[], since 1.31
	enabled: true, // boolean
	ariaDescription: undefined, // string
	maxVisibleItems: 0, // int
	pageSize: 5, // int, since 1.25.0
	tooltip: undefined, // sap.ui.core.TooltipBase
	customData: [], // sap.ui.core.CustomData
	dependents: [], // sap.ui.core.Element, since 1.19
	items: [], // sap.ui.unified.MenuItemBase
	ariaLabelledBy: [], // sap.ui.core.Control, since 1.26.3
	validateFieldGroup: [function (oEvent) {
		var ${control} = oEvent.getSource();
	}, this],
	itemSelect: [function (oEvent) {
		var ${control} = oEvent.getSource();
	}, this]
})
]]></jsTemplate>
	<xmlTemplate><![CDATA[<ColumnMenu xmlns="sap.ui.table"
	id="${id}"
	busy="false"
	busyIndicatorDelay="1000"
	visible="true"
	fieldGroupIds=""
	enabled="true"
	ariaDescription=""
	maxVisibleItems="0"
	pageSize="5"
	ariaLabelledBy=""
	validateFieldGroup=""
	itemSelect="">
		<tooltip></tooltip> <!-- sap.ui.core.TooltipBase -->
		<dependents></dependents> <!-- sap.ui.core.Element, since 1.19 -->
		<items></items> <!-- sap.ui.unified.MenuItemBase -->
</ColumnMenu>
]]></xmlTemplate>
</Template>
<Template name="sap.ui.table.Row" alias="Row">
	<jsTemplate><![CDATA[new sap.ui.table.Row({
	id: "${id}", // sap.ui.core.ID
	tooltip: undefined, // sap.ui.core.TooltipBase
	customData: [], // sap.ui.core.CustomData
	dependents: [], // sap.ui.core.Element, since 1.19
	cells: [] // sap.ui.core.Control
})
]]></jsTemplate>
	<xmlTemplate><![CDATA[<Row xmlns="sap.ui.table"
	id="${id}">
		<tooltip></tooltip> <!-- sap.ui.core.TooltipBase -->
		<dependents></dependents> <!-- sap.ui.core.Element, since 1.19 -->
		<cells></cells> <!-- sap.ui.core.Control -->
</Row>
]]></xmlTemplate>
</Template>
<Template name="sap.ui.table.RowAction" alias="RowAction,Action">
	<jsTemplate><![CDATA[new sap.ui.table.RowAction({
	id: "${id}", // sap.ui.core.ID
	busy: false, // boolean
	busyIndicatorDelay: 1000, // int
	visible: true, // boolean
	fieldGroupIds: [], // string[], since 1.31
	visible: true, // boolean
	tooltip: undefined, // sap.ui.core.TooltipBase
	customData: [], // sap.ui.core.CustomData
	dependents: [], // sap.ui.core.Element, since 1.19
	items: [], // sap.ui.table.RowActionItem
	validateFieldGroup: [function (oEvent) {
		var ${control} = oEvent.getSource();
	}, this]
})
]]></jsTemplate>
	<xmlTemplate><![CDATA[<RowAction xmlns="sap.ui.table"
	id="${id}"
	busy="false"
	busyIndicatorDelay="1000"
	visible="true"
	fieldGroupIds=""
	visible="true"
	validateFieldGroup="">
		<tooltip></tooltip> <!-- sap.ui.core.TooltipBase -->
		<dependents></dependents> <!-- sap.ui.core.Element, since 1.19 -->
		<items></items> <!-- sap.ui.table.RowActionItem -->
</RowAction>
]]></xmlTemplate>
</Template>
<Template name="sap.ui.table.RowActionItem" alias="RowActionItem,Item">
	<jsTemplate><![CDATA[new sap.ui.table.RowActionItem({
	id: "${id}", // sap.ui.core.ID
	icon: undefined, // sap.ui.core.URI
	visible: true, // boolean
	text: "", // string
	type: sap.ui.table.RowActionType.Custom, // sap.ui.table.RowActionType
	tooltip: undefined, // sap.ui.core.TooltipBase
	customData: [], // sap.ui.core.CustomData
	dependents: [], // sap.ui.core.Element, since 1.19
	press: [function (oEvent) {
		var ${control} = oEvent.getSource();
	}, this]
})
]]></jsTemplate>
	<xmlTemplate><![CDATA[<RowActionItem xmlns="sap.ui.table"
	id="${id}"
	icon=""
	visible="true"
	text=""
	type="Custom"
	press="">
		<tooltip></tooltip> <!-- sap.ui.core.TooltipBase -->
		<dependents></dependents> <!-- sap.ui.core.Element, since 1.19 -->
</RowActionItem>
]]></xmlTemplate>
</Template>
<Template name="sap.ui.table.Table" alias="Table">
	<jsTemplate><![CDATA[new sap.ui.table.Table({
	id: "${id}", // sap.ui.core.ID
	busy: false, // boolean
	busyIndicatorDelay: 1000, // int
	visible: true, // boolean
	fieldGroupIds: [], // string[], since 1.31
	width: "auto", // sap.ui.core.CSSSize
	rowHeight: undefined, // int
	columnHeaderHeight: undefined, // int
	columnHeaderVisible: true, // boolean
	visibleRowCount: 10, // int
	firstVisibleRow: 0, // int
	selectionMode: sap.ui.table.SelectionMode.MultiToggle, // sap.ui.table.SelectionMode
	selectionBehavior: sap.ui.table.SelectionBehavior.RowSelector, // sap.ui.table.SelectionBehavior
	selectedIndex: -1, // int
	editable: true, // boolean
	navigationMode: sap.ui.table.NavigationMode.Scrollbar, // sap.ui.table.NavigationMode
	threshold: 100, // int
	enableColumnReordering: true, // boolean
	enableGrouping: false, // boolean
	showColumnVisibilityMenu: false, // boolean
	showNoData: true, // boolean
	visibleRowCountMode: sap.ui.table.VisibleRowCountMode.Fixed, // sap.ui.table.VisibleRowCountMode, since 1.9.2
	minAutoRowCount: 5, // int
	fixedColumnCount: 0, // int
	fixedRowCount: 0, // int
	fixedBottomRowCount: 0, // int, since 1.18.7
	enableColumnFreeze: false, // boolean, since 1.21.0
	enableCellFilter: false, // boolean, since 1.21.0
	showOverlay: false, // boolean, since 1.21.2
	enableSelectAll: true, // boolean, since 1.23.0
	enableCustomFilter: false, // boolean, since 1.23.0
	enableBusyIndicator: false, // boolean, since 1.27.0
	rowActionCount: 0, // int, since 1.45.0
	tooltip: undefined, // sap.ui.core.TooltipBase
	customData: [], // sap.ui.core.CustomData
	dependents: [], // sap.ui.core.Element, since 1.19
	title: undefined, // sap.ui.core.Control
	footer: undefined, // sap.ui.core.Control
	toolbar: undefined, // sap.ui.core.Toolbar
	extension: [], // sap.ui.core.Control
	columns: [], // sap.ui.table.Column
	rows: [], // sap.ui.table.Row
	noData: undefined, // sap.ui.core.Control
	rowActionTemplate: undefined, // sap.ui.table.RowAction
	groupBy: undefined, // sap.ui.table.Column
	ariaLabelledBy: [], // sap.ui.core.Control
	validateFieldGroup: [function (oEvent) {
		var ${control} = oEvent.getSource();
	}, this],
	rowSelectionChange: [function (oEvent) {
		var ${control} = oEvent.getSource();
	}, this],
	columnSelect: [function (oEvent) {
		var ${control} = oEvent.getSource();
	}, this],
	columnResize: [function (oEvent) {
		var ${control} = oEvent.getSource();
	}, this],
	columnMove: [function (oEvent) {
		var ${control} = oEvent.getSource();
	}, this],
	sort: [function (oEvent) {
		var ${control} = oEvent.getSource();
	}, this],
	filter: [function (oEvent) {
		var ${control} = oEvent.getSource();
	}, this],
	group: [function (oEvent) {
		var ${control} = oEvent.getSource();
	}, this],
	columnVisibility: [function (oEvent) {
		var ${control} = oEvent.getSource();
	}, this],
	cellClick: [function (oEvent) {
		var ${control} = oEvent.getSource();
	}, this], // since 1.21.0
	cellContextmenu: [function (oEvent) {
		var ${control} = oEvent.getSource();
	}, this], // since 1.21.0
	columnFreeze: [function (oEvent) {
		var ${control} = oEvent.getSource();
	}, this], // since 1.21.0
	customFilter: [function (oEvent) {
		var ${control} = oEvent.getSource();
	}, this], // since 1.23.0
	firstVisibleRowChanged: [function (oEvent) {
		var ${control} = oEvent.getSource();
	}, this], // since 1.37.0
	busyStateChanged: [function (oEvent) {
		var ${control} = oEvent.getSource();
	}, this] // since 1.37.0
})
]]></jsTemplate>
	<xmlTemplate><![CDATA[<Table xmlns="sap.ui.table"
	id="${id}"
	busy="false"
	busyIndicatorDelay="1000"
	visible="true"
	fieldGroupIds=""
	width="auto"
	rowHeight=""
	columnHeaderHeight=""
	columnHeaderVisible="true"
	visibleRowCount="10"
	firstVisibleRow="0"
	selectionMode="MultiToggle"
	selectionBehavior="RowSelector"
	selectedIndex="-1"
	editable="true"
	navigationMode="Scrollbar"
	threshold="100"
	enableColumnReordering="true"
	enableGrouping="false"
	showColumnVisibilityMenu="false"
	showNoData="true"
	visibleRowCountMode="Fixed"
	minAutoRowCount="5"
	fixedColumnCount="0"
	fixedRowCount="0"
	fixedBottomRowCount="0"
	enableColumnFreeze="false"
	enableCellFilter="false"
	showOverlay="false"
	enableSelectAll="true"
	enableCustomFilter="false"
	enableBusyIndicator="false"
	rowActionCount="0"
	groupBy=""
	ariaLabelledBy=""
	validateFieldGroup=""
	rowSelectionChange=""
	columnSelect=""
	columnResize=""
	columnMove=""
	sort=""
	filter=""
	group=""
	columnVisibility=""
	cellClick=""
	cellContextmenu=""
	columnFreeze=""
	customFilter=""
	firstVisibleRowChanged=""
	busyStateChanged="">
		<tooltip></tooltip> <!-- sap.ui.core.TooltipBase -->
		<dependents></dependents> <!-- sap.ui.core.Element, since 1.19 -->
		<title></title> <!-- sap.ui.core.Control -->
		<footer></footer> <!-- sap.ui.core.Control -->
		<toolbar></toolbar> <!-- sap.ui.core.Toolbar -->
		<extension></extension> <!-- sap.ui.core.Control -->
		<columns></columns> <!-- sap.ui.table.Column -->
		<rows></rows> <!-- sap.ui.table.Row -->
		<noData></noData> <!-- sap.ui.core.Control -->
		<rowActionTemplate></rowActionTemplate> <!-- sap.ui.table.RowAction -->
</Table>
]]></xmlTemplate>
</Template>
<Template name="sap.ui.table.TreeTable" alias="TreeTable,Table">
	<jsTemplate><![CDATA[new sap.ui.table.TreeTable({
	id: "${id}", // sap.ui.core.ID
	busy: false, // boolean
	busyIndicatorDelay: 1000, // int
	visible: true, // boolean
	fieldGroupIds: [], // string[], since 1.31
	width: "auto", // sap.ui.core.CSSSize
	rowHeight: undefined, // int
	columnHeaderHeight: undefined, // int
	columnHeaderVisible: true, // boolean
	visibleRowCount: 10, // int
	firstVisibleRow: 0, // int
	selectionMode: sap.ui.table.SelectionMode.MultiToggle, // sap.ui.table.SelectionMode
	selectionBehavior: sap.ui.table.SelectionBehavior.RowSelector, // sap.ui.table.SelectionBehavior
	selectedIndex: -1, // int
	editable: true, // boolean
	navigationMode: sap.ui.table.NavigationMode.Scrollbar, // sap.ui.table.NavigationMode
	threshold: 100, // int
	enableColumnReordering: true, // boolean
	enableGrouping: false, // boolean
	showColumnVisibilityMenu: false, // boolean
	showNoData: true, // boolean
	visibleRowCountMode: sap.ui.table.VisibleRowCountMode.Fixed, // sap.ui.table.VisibleRowCountMode, since 1.9.2
	minAutoRowCount: 5, // int
	fixedColumnCount: 0, // int
	fixedRowCount: 0, // int
	fixedBottomRowCount: 0, // int, since 1.18.7
	enableColumnFreeze: false, // boolean, since 1.21.0
	enableCellFilter: false, // boolean, since 1.21.0
	showOverlay: false, // boolean, since 1.21.2
	enableSelectAll: true, // boolean, since 1.23.0
	enableCustomFilter: false, // boolean, since 1.23.0
	enableBusyIndicator: false, // boolean, since 1.27.0
	rowActionCount: 0, // int, since 1.45.0
	expandFirstLevel: false, // boolean
	useGroupMode: false, // boolean
	groupHeaderProperty: undefined, // string
	collapseRecursive: true, // boolean
	rootLevel: 0, // int
	tooltip: undefined, // sap.ui.core.TooltipBase
	customData: [], // sap.ui.core.CustomData
	dependents: [], // sap.ui.core.Element, since 1.19
	title: undefined, // sap.ui.core.Control
	footer: undefined, // sap.ui.core.Control
	toolbar: undefined, // sap.ui.core.Toolbar
	extension: [], // sap.ui.core.Control
	columns: [], // sap.ui.table.Column
	rows: [], // sap.ui.table.Row
	noData: undefined, // sap.ui.core.Control
	rowActionTemplate: undefined, // sap.ui.table.RowAction
	groupBy: undefined, // sap.ui.table.Column
	ariaLabelledBy: [], // sap.ui.core.Control
	validateFieldGroup: [function (oEvent) {
		var ${control} = oEvent.getSource();
	}, this],
	rowSelectionChange: [function (oEvent) {
		var ${control} = oEvent.getSource();
	}, this],
	columnSelect: [function (oEvent) {
		var ${control} = oEvent.getSource();
	}, this],
	columnResize: [function (oEvent) {
		var ${control} = oEvent.getSource();
	}, this],
	columnMove: [function (oEvent) {
		var ${control} = oEvent.getSource();
	}, this],
	sort: [function (oEvent) {
		var ${control} = oEvent.getSource();
	}, this],
	filter: [function (oEvent) {
		var ${control} = oEvent.getSource();
	}, this],
	group: [function (oEvent) {
		var ${control} = oEvent.getSource();
	}, this],
	columnVisibility: [function (oEvent) {
		var ${control} = oEvent.getSource();
	}, this],
	cellClick: [function (oEvent) {
		var ${control} = oEvent.getSource();
	}, this], // since 1.21.0
	cellContextmenu: [function (oEvent) {
		var ${control} = oEvent.getSource();
	}, this], // since 1.21.0
	columnFreeze: [function (oEvent) {
		var ${control} = oEvent.getSource();
	}, this], // since 1.21.0
	customFilter: [function (oEvent) {
		var ${control} = oEvent.getSource();
	}, this], // since 1.23.0
	firstVisibleRowChanged: [function (oEvent) {
		var ${control} = oEvent.getSource();
	}, this], // since 1.37.0
	busyStateChanged: [function (oEvent) {
		var ${control} = oEvent.getSource();
	}, this], // since 1.37.0
	toggleOpenState: [function (oEvent) {
		var ${control} = oEvent.getSource();
	}, this]
})
]]></jsTemplate>
	<xmlTemplate><![CDATA[<TreeTable xmlns="sap.ui.table"
	id="${id}"
	busy="false"
	busyIndicatorDelay="1000"
	visible="true"
	fieldGroupIds=""
	width="auto"
	rowHeight=""
	columnHeaderHeight=""
	columnHeaderVisible="true"
	visibleRowCount="10"
	firstVisibleRow="0"
	selectionMode="MultiToggle"
	selectionBehavior="RowSelector"
	selectedIndex="-1"
	editable="true"
	navigationMode="Scrollbar"
	threshold="100"
	enableColumnReordering="true"
	enableGrouping="false"
	showColumnVisibilityMenu="false"
	showNoData="true"
	visibleRowCountMode="Fixed"
	minAutoRowCount="5"
	fixedColumnCount="0"
	fixedRowCount="0"
	fixedBottomRowCount="0"
	enableColumnFreeze="false"
	enableCellFilter="false"
	showOverlay="false"
	enableSelectAll="true"
	enableCustomFilter="false"
	enableBusyIndicator="false"
	rowActionCount="0"
	expandFirstLevel="false"
	useGroupMode="false"
	groupHeaderProperty=""
	collapseRecursive="true"
	rootLevel="0"
	groupBy=""
	ariaLabelledBy=""
	validateFieldGroup=""
	rowSelectionChange=""
	columnSelect=""
	columnResize=""
	columnMove=""
	sort=""
	filter=""
	group=""
	columnVisibility=""
	cellClick=""
	cellContextmenu=""
	columnFreeze=""
	customFilter=""
	firstVisibleRowChanged=""
	busyStateChanged=""
	toggleOpenState="">
		<tooltip></tooltip> <!-- sap.ui.core.TooltipBase -->
		<dependents></dependents> <!-- sap.ui.core.Element, since 1.19 -->
		<title></title> <!-- sap.ui.core.Control -->
		<footer></footer> <!-- sap.ui.core.Control -->
		<toolbar></toolbar> <!-- sap.ui.core.Toolbar -->
		<extension></extension> <!-- sap.ui.core.Control -->
		<columns></columns> <!-- sap.ui.table.Column -->
		<rows></rows> <!-- sap.ui.table.Row -->
		<noData></noData> <!-- sap.ui.core.Control -->
		<rowActionTemplate></rowActionTemplate> <!-- sap.ui.table.RowAction -->
</TreeTable>
]]></xmlTemplate>
</Template>
</Library>
