<?xml version='1.0' encoding='utf-8'?>
    <GateDocument version="3">
    <!-- The document's features-->

    <GateDocumentFeatures>
        <Feature>
          <Name className="java.lang.String">parsingError</Name>
          <Value className="java.lang.Boolean">true</Value>
        </Feature>
        <Feature>
          <Name className="java.lang.String">MimeType</Name>
          <Value className="java.lang.String">text/xml</Value>
        </Feature>
        <Feature>
            <Name className="java.lang.String">source</Name>
            <Value className="java.lang.String">http://www.usatoday.com/story/sports/motor/formula1/2016/11/13/brazils-massa-crashes-but-gets-warm-farewell-at-home-gp/93771246/</Value>
        </Feature>
        <Feature>
            <Name className="java.lang.String">pubdate</Name>
            <Value className="java.lang.String">2016-11-13 21:09:21</Value>
        </Feature>
    </GateDocumentFeatures>
    <!-- The document content area with serialized nodes -->

    <TextWithNodes><Node id="0"/>Brazil's Massa crashes but gets warm farewell at home GP<Node id="56"/>
<Node id="57"/>Williams' veteran driver <Node id="82"/>Felipe Massa<Node id="94"/> <Node id="95"/>failed to finish his last race<Node id="125"/> in front of his home crowd at <Node id="156"/>Interlagos<Node id="166"/> on <Node id="170"/>Sunday<Node id="176"/>, but he still earned a warm and emotional goodbye<Node id="226"/>
<Node id="227"/>Williams' Felipe Massa of Brazil cries after he had to withdraw from the race <Node id="305"/>due to car problems<Node id="324"/> during the Brazilian Formula One Grand Prix at the Interlagos race track in <Node id="401"/>Sao Paulo, Brazil<Node id="418"/>, <Node id="420"/>Sunday, Nov. 13, 2016<Node id="441"/>. (Paulo Whitaker/Pool via AP) (Photo: The Associated Press)
SAO PAULO (AP) — Williams' veteran driver Felipe Massa failed to finish his last race in front of his home crowd at Interlagos on Sunday, but he still earned a warm and emotional goodbye.
In a Brazilian Grand Prix deeply impacted by rain, Massa crashed out in the 48th of 71 laps when he was in 14th position.
In tears, the 35-year-old driver walked through the pit lane wrapped in a Brazilian flag and was greeted by his wife Anna Raffaela, his son Felipinho, a rowdy local crowd and members of all teams.
"I am leaving with my head up and my heart still aching," Massa told reporters by the pit lane. "I apologize to this crowd, this is not the result that I expected here. I can only thank them for the love, for all the emotions that I felt."
The Brazilian driver also said he expects to be part of a different racing series next year, without providing further details.
Massa has 11 Grand Prix career wins, including two in Brazil. Two weeks from now, he will make his final appearance in a Formula 1 car at the season-finisher in Abu Dhabi, after reaching his 250th start.
Massa's F1 career began in 2002 as a member of Sauber. He shone at Ferrari, the team that gave him his best chance at the title race in 2008. At a Brazilian GP that he won, Massa lost the crown to Lewis Hamilton after the British driver made a key overtake on the very last lap.
One year later Massa's life was put at serious risk after he was struck on the head by a wheel at the Hungarian Grand Prix. He stayed in the hospital for days.
Massa joined Williams in 2014. In the current season he is 11th with 51 points.
With his retirement and the difficulties for Felipe Nasr of Sauber to renew his contract, there is a chance that no Brazilian drivers will be on the grid in 2017. That would be the first time in 48 years.
There are no other Brazilian drivers in Europe being considered for a place at the moment.
Sunday's race was won by three-time series champion Hamilton, forcing a showdown for the season title with Mercedes teammate Nico Rosberg in Abu Dhabi.
Copyright 2016 The Associated Press. All rights reserved. This material may not be published, broadcast, rewritten or redistributed.<Node id="2682"/>

    </TextWithNodes>
    <!-- The default annotation set -->

    <AnnotationSet>
		<Annotation Id="7" Type="FiveW" StartNode="82" EndNode="94">
                                <Feature>
                                    <Name className="java.lang.String">accuracy</Name>
                                    <Value className="java.lang.String">1</Value>
                                </Feature>
                                <Feature>
                                    <Name className="java.lang.String">id</Name>
                                    <Value className="java.lang.String">1</Value>
                                </Feature>
                                <Feature>
                                    <Name className="java.lang.String">question</Name>
                                    <Value className="java.lang.String">who</Value>
                                </Feature>
		</Annotation>
		<Annotation Id="8" Type="FiveW" StartNode="95" EndNode="125">
                                <Feature>
                                    <Name className="java.lang.String">id</Name>
                                    <Value className="java.lang.String">1</Value>
                                </Feature>
                                <Feature>
                                    <Name className="java.lang.String">question</Name>
                                    <Value className="java.lang.String">what</Value>
                                </Feature>
		</Annotation>
		<Annotation Id="9" Type="FiveW" StartNode="156" EndNode="166">
                                <Feature>
                                    <Name className="java.lang.String">accuracy</Name>
                                    <Value className="java.lang.String">1</Value>
                                </Feature>
                                <Feature>
                                    <Name className="java.lang.String">id</Name>
                                    <Value className="java.lang.String">1</Value>
                                </Feature>
                                <Feature>
                                    <Name className="java.lang.String">question</Name>
                                    <Value className="java.lang.String">where</Value>
                                </Feature>
		</Annotation>
		<Annotation Id="10" Type="FiveW" StartNode="170" EndNode="176">
                                <Feature>
                                    <Name className="java.lang.String">accuracy</Name>
                                    <Value className="java.lang.String">2</Value>
                                </Feature>
                                <Feature>
                                    <Name className="java.lang.String">id</Name>
                                    <Value className="java.lang.String">1</Value>
                                </Feature>
                                <Feature>
                                    <Name className="java.lang.String">question</Name>
                                    <Value className="java.lang.String">when</Value>
                                </Feature>
		</Annotation>
		<Annotation Id="11" Type="FiveW" StartNode="305" EndNode="324">
                                <Feature>
                                    <Name className="java.lang.String">id</Name>
                                    <Value className="java.lang.String">1</Value>
                                </Feature>
                                <Feature>
                                    <Name className="java.lang.String">question</Name>
                                    <Value className="java.lang.String">why</Value>
                                </Feature>
		</Annotation>
		<Annotation Id="12" Type="FiveW" StartNode="401" EndNode="418">
                                <Feature>
                                    <Name className="java.lang.String">accuracy</Name>
                                    <Value className="java.lang.String">2</Value>
                                </Feature>
                                <Feature>
                                    <Name className="java.lang.String">id</Name>
                                    <Value className="java.lang.String">1</Value>
                                </Feature>
                                <Feature>
                                    <Name className="java.lang.String">question</Name>
                                    <Value className="java.lang.String">where</Value>
                                </Feature>
		</Annotation>
		<Annotation Id="13" Type="FiveW" StartNode="420" EndNode="441">
                                <Feature>
                                    <Name className="java.lang.String">accuracy</Name>
                                    <Value className="java.lang.String">1</Value>
                                </Feature>
                                <Feature>
                                    <Name className="java.lang.String">id</Name>
                                    <Value className="java.lang.String">1</Value>
                                </Feature>
                                <Feature>
                                    <Name className="java.lang.String">question</Name>
                                    <Value className="java.lang.String">when</Value>
                                </Feature>
		</Annotation>
        <Annotation Id="14" Type="TextSection" StartNode="0" EndNode="56">
            <Feature>
                <Name className="java.lang.String">section</Name>
                <Value className="java.lang.String">title</Value>
            </Feature>
        </Annotation>
        <Annotation Id="15" Type="TextSection" StartNode="57" EndNode="226">
            <Feature>
                <Name className="java.lang.String">section</Name>
                <Value className="java.lang.String">description</Value>
            </Feature>
        </Annotation>
        <Annotation Id="16" Type="TextSection" StartNode="227" EndNode="2682">
            <Feature>
                <Name className="java.lang.String">section</Name>
                <Value className="java.lang.String">text</Value>
            </Feature>
        </Annotation>
    </AnnotationSet>
    </GateDocument>
                    