{
  "authors": [
    "Tracy You For Mailonline"
  ],
  "date_download": "2017-11-30T19:49:13",
  "date_modify": null,
  "date_publish": "2016-11-08T17:08:57",
  "description": "Five-year-old Zhao Zicong fell into the 12-inch-wide well by accident while working with his father in a village in central China. The condition of the boy remains unknown as rescue operation goes on.",
  "filename": "http%3A%2F%2Fwww.dailymail.co.uk%2Fnews%2Farticle-3916560%2FDramatic-footage-shows-rescuers-using-eighty-diggers-save-boy-fell-130ft-deep-picking-cabbages-Chinese-farm.html.json",
  "image_url": "http://i.dailymail.co.uk/i/pix/2016/11/08/17/3A2E767900000578-0-image-a-27_1478624459817.jpg",
  "language": "en",
  "localpath": null,
  "source_domain": "www.dailymail.co.uk",
  "text": "A team of rescuers and diggers have worked\nA large-scale rescue operation is underway in China to save a little boy who fell into a 40-metre-deep well (131 feet) while picking cabbages with his father.\nThe six-year-old, whose condition remains unknown, plummeted into the well at around 11am local time on Sunday in a rural village of Hebei Province, according to Chinese media.\nAround 80 diggers are working around the clock at the scene in a bid to save the child, who has been trapped for around 50 hours by now.\nExcavators work at the rescue site in Zhongmengchang Village of Lixian County in Baoding\nThe rescue team are trying to save a boy who fell into a dried well in Baoding on November 6\nA six-year-old boy fell into a deserted well measuring 130ft deep and 12 inches wide\nA large rescue team, including police, firemen and paramedics, have been sent to the scene\nThe boy, named Zhao Zicong by Chinese media, was fell into the deserted well located on a farm in the village of Zhongmengchang in Lixian County, Hebei's Baoding city.\nAccording to The Beijing News, little Zhao was harvesting cabbages with his father when he fell by accident.\nThe dry well measured just 30 centimetres wide (11.8 inches).\nThe boy's grandfather told a reporter from The Beijing News that the well was located near their house and had been used to irrigate the nearby fields.\nThe man also said that the well was about 40 metres deep (131 feet) and had been abandoned for around five years.\nAfter the family alerted the local authority, a team of rescuers, including police officers, firefighters, paramedics and local volunteers were sent to the scene to search for the trapped boy.\nOver 80 diggers have been dispatched for the rescue operation, according to local media\nThe heavy duty vehicles are working around the clock to save the child since fell on Sunday\nThe heavy-duty vehicles have dug a crater of around 330 feet in diametre around the well\nIt remains unknown whether or not Zhao is still alive as rescuers carry on searching\nMore than 80 diggers have been sent to the farm to remove earth around the well.\nRescuers have put metal tubes around the well to prevent the boy from being hurt by the diggers.\nIn addition, oxygen is being pumped into the bottom of the well by the rescuers.\nAn aerial video posted by QQ.com shows the heavy-duty vehicles have dug a crater of around 100 metres (328 feet) in diametre around the well.\nThe rescue team were less than 10 metres (33 feet) from reaching the bottom of the well.\nRescuers have used life detectors, but they failed to find any signs of life, according to local reports.",
  "title": "Footage shows rescuers using diggers to save Zhao Zicong who fell into a well on a Chinese farm",
  "title_page": null,
  "title_rss": null,
  "url": "http://www.dailymail.co.uk/news/article-3916560/Dramatic-footage-shows-rescuers-using-eighty-diggers-save-boy-fell-130ft-deep-picking-cabbages-Chinese-farm.html",
  "newsCluster": {
    "CategoryId": 1,
    "Category": "world",
    "TopicId": 2,
    "Topic": "legancy",
    "EventId": 62,
    "Event": "china_boy_well"
  },
  "dId": "7b1f91bcb6dc19b7db1e86930b69f5e65ff5984db394440468f7fca4",
  "fiveWoneH": {
    "where": {
      "extracted": [
        {
          "parts": [
            [
              {
                "nlpToken": {
                  "index": 21,
                  "word": "China",
                  "originalText": "China",
                  "lemma": "China",
                  "characterOffsetBegin": 221,
                  "characterOffsetEnd": 226,
                  "pos": "NNP",
                  "ner": "LOCATION",
                  "speaker": "PER0",
                  "before": " ",
                  "after": ""
                },
                "aida": [
                  {
                    "mention": {
                      "allEntities": [
                        {
                          "kbIdentifier": "YAGO:China",
                          "disambiguationScore": "0.376"
                        }
                      ],
                      "offset": 221,
                      "name": "China",
                      "length": 5,
                      "bestEntity": {
                        "kbIdentifier": "YAGO:China",
                        "disambiguationScore": "0.376"
                      }
                    },
                    "bestEntityMetadata": {
                      "knowledgebase": "YAGO",
                      "depictionurl": "http://upload.wikimedia.org/wikipedia/commons/f/fa/Flag_of_the_People%27s_Republic_of_China.svg",
                      "depictionthumbnailurl": "http://upload.wikimedia.org/wikipedia/commons/thumbFlag_of_the_People%27s_Republic_of_China.svg/200px-Flag_of_the_People%27s_Republic_of_China.svg",
                      "importance": 9.192157028782871e-06,
                      "entityId": "China",
                      "type": [
                        "YAGO_wordnet_system_108435388",
                        "YAGO_wordnet_district_108552138",
                        "YAGO_wikicategory_East_Asian_countries",
                        "YAGO_yagoPermanentlyLocatedEntity",
                        "YAGO_yagoLegalActorGeo",
                        "YAGO_wordnet_state_108654360",
                        "YAGO_wordnet_country_108544813",
                        "YAGO_wikicategory_Member_states_of_the_United_Nations",
                        "YAGO_wordnet_economy_108366753",
                        "YAGO_wikicategory_States_and_territories_established_in_1949",
                        "YAGO_wikicategory_Communist_states",
                        "YAGO_wordnet_abstraction_100002137",
                        "YAGO_wordnet_region_108630985",
                        "YAGO_yagoGeoEntity",
                        "YAGO_wordnet_physical_entity_100001930",
                        "YAGO_wikicategory_Central_Asian_countries",
                        "YAGO_wordnet_entity_100001740",
                        "YAGO_wikicategory_Single\\u002dparty_states",
                        "YAGO_wordnet_object_100002684",
                        "YAGO_wordnet_group_100031264",
                        "YAGO_wordnet_location_100027167",
                        "YAGO_wordnet_administrative_district_108491826",
                        "YAGO_wikicategory_Chinese\\u002dspeaking_countries_and_territories"
                      ],
                      "readableRepr": "China",
                      "url": "http://en.wikipedia.org/wiki/China"
                    }
                  }
                ]
              },
              "NNP"
            ]
          ],
          "score": 0.6755345451640522,
          "text": "China",
          "enhancement": {
            "openstreetmap_nominatim": {
              "osm_id": "5605656",
              "boundingbox": [
                25.0671341,
                25.9161824,
                -99.4612273,
                -98.421576
              ],
              "licence": "Data \u00a9 OpenStreetMap contributors, ODbL 1.0. http://www.openstreetmap.org/copyright",
              "importance": 0.2225,
              "icon": "https://nominatim.openstreetmap.org/images/mapicons/poi_boundary_administrative.p.20.png",
              "osm_type": "relation",
              "display_name": "China, Nuevo Le\u00f3n, M\u00e9xico",
              "lat": "25.4915799",
              "type": "administrative",
              "place_id": "179360170",
              "lon": "-98.9811115045569",
              "class": "boundary"
            }
          },
          "nlpIndexSentence": 1
        }
      ],
      "label": "where"
    },
    "when": {
      "extracted": [
        {
          "parts": [
            [
              {
                "nlpToken": {
                  "index": 15,
                  "word": "11am",
                  "originalText": "11am",
                  "lemma": "11am",
                  "characterOffsetBegin": 586,
                  "characterOffsetEnd": 590,
                  "pos": "JJ",
                  "ner": "TIME",
                  "normalizedNER": "2016-11-08T11:00",
                  "speaker": "PER0",
                  "before": " ",
                  "after": " ",
                  "timex": {
                    "tid": "t3",
                    "type": "TIME",
                    "value": "2016-11-08T11:00"
                  }
                },
                "heideltime": [
                  {
                    "@tid": "t4",
                    "@type": "TIME",
                    "@value": "XXXX-XX-XXT11:00",
                    "@mod": "APPROX",
                    "#text": "around 11am",
                    "characterOffset": [
                      579,
                      590
                    ]
                  }
                ]
              },
              "JJ"
            ]
          ],
          "score": 0.43043089499684417,
          "text": "11am",
          "enhancement": {
            "timex": {
              "start_date": "2016-11-08T11:00:00",
              "end_date": "2016-11-08T11:00:59"
            }
          },
          "nlpIndexSentence": 5
        }
      ],
      "label": "when"
    },
    "who": {
      "extracted": [
        {
          "parts": [
            [
              {
                "nlpToken": {
                  "index": 1,
                  "word": "Five-year-old",
                  "originalText": "Five-year-old",
                  "lemma": "five-year-old",
                  "characterOffsetBegin": 97,
                  "characterOffsetEnd": 110,
                  "pos": "JJ",
                  "ner": "DURATION",
                  "normalizedNER": "P5Y",
                  "speaker": "PER0",
                  "before": " ",
                  "after": " ",
                  "timex": {
                    "tid": "t1",
                    "type": "DURATION",
                    "value": "P5Y"
                  }
                }
              },
              "JJ"
            ],
            [
              {
                "nlpToken": {
                  "index": 2,
                  "word": "Zhao",
                  "originalText": "Zhao",
                  "lemma": "Zhao",
                  "characterOffsetBegin": 111,
                  "characterOffsetEnd": 115,
                  "pos": "NNP",
                  "ner": "PERSON",
                  "speaker": "PER0",
                  "before": " ",
                  "after": " "
                },
                "aida": [
                  {
                    "mention": {
                      "allEntities": [],
                      "offset": 111,
                      "name": "Zhao Zicong",
                      "length": 11
                    },
                    "bestEntityMetadata": null
                  }
                ]
              },
              "NNP"
            ],
            [
              {
                "nlpToken": {
                  "index": 3,
                  "word": "Zicong",
                  "originalText": "Zicong",
                  "lemma": "Zicong",
                  "characterOffsetBegin": 116,
                  "characterOffsetEnd": 122,
                  "pos": "NNP",
                  "ner": "PERSON",
                  "speaker": "PER0",
                  "before": " ",
                  "after": " "
                },
                "aida": [
                  {
                    "mention": {
                      "allEntities": [],
                      "offset": 111,
                      "name": "Zhao Zicong",
                      "length": 11
                    },
                    "bestEntityMetadata": null
                  }
                ]
              },
              "NNP"
            ]
          ],
          "score": 1.0,
          "text": "Five-year-old Zhao Zicong",
          "nlpIndexSentence": 1
        }
      ],
      "label": "who"
    },
    "what": {
      "extracted": [
        {
          "parts": [
            [
              {
                "nlpToken": {
                  "index": 4,
                  "word": "fell",
                  "originalText": "fell",
                  "lemma": "fall",
                  "characterOffsetBegin": 123,
                  "characterOffsetEnd": 127,
                  "pos": "VBD",
                  "ner": "O",
                  "speaker": "PER0",
                  "before": " ",
                  "after": " "
                }
              },
              "VBD"
            ],
            [
              {
                "nlpToken": {
                  "index": 5,
                  "word": "into",
                  "originalText": "into",
                  "lemma": "into",
                  "characterOffsetBegin": 128,
                  "characterOffsetEnd": 132,
                  "pos": "IN",
                  "ner": "O",
                  "speaker": "PER0",
                  "before": " ",
                  "after": " "
                }
              },
              "IN"
            ],
            [
              {
                "nlpToken": {
                  "index": 6,
                  "word": "the",
                  "originalText": "the",
                  "lemma": "the",
                  "characterOffsetBegin": 133,
                  "characterOffsetEnd": 136,
                  "pos": "DT",
                  "ner": "O",
                  "speaker": "PER0",
                  "before": " ",
                  "after": " "
                }
              },
              "DT"
            ],
            [
              {
                "nlpToken": {
                  "index": 7,
                  "word": "12-inch-wide",
                  "originalText": "12-inch-wide",
                  "lemma": "12-inch-wide",
                  "characterOffsetBegin": 137,
                  "characterOffsetEnd": 149,
                  "pos": "JJ",
                  "ner": "O",
                  "speaker": "PER0",
                  "before": " ",
                  "after": " "
                }
              },
              "JJ"
            ],
            [
              {
                "nlpToken": {
                  "index": 8,
                  "word": "well",
                  "originalText": "well",
                  "lemma": "well",
                  "characterOffsetBegin": 150,
                  "characterOffsetEnd": 154,
                  "pos": "NN",
                  "ner": "O",
                  "speaker": "PER0",
                  "before": " ",
                  "after": " "
                }
              },
              "NN"
            ],
            [
              {
                "nlpToken": {
                  "index": 9,
                  "word": "by",
                  "originalText": "by",
                  "lemma": "by",
                  "characterOffsetBegin": 155,
                  "characterOffsetEnd": 157,
                  "pos": "IN",
                  "ner": "O",
                  "speaker": "PER0",
                  "before": " ",
                  "after": " "
                }
              },
              "IN"
            ],
            [
              {
                "nlpToken": {
                  "index": 10,
                  "word": "accident",
                  "originalText": "accident",
                  "lemma": "accident",
                  "characterOffsetBegin": 158,
                  "characterOffsetEnd": 166,
                  "pos": "NN",
                  "ner": "O",
                  "speaker": "PER0",
                  "before": " ",
                  "after": " "
                }
              },
              "NN"
            ],
            [
              {
                "nlpToken": {
                  "index": 11,
                  "word": "while",
                  "originalText": "while",
                  "lemma": "while",
                  "characterOffsetBegin": 167,
                  "characterOffsetEnd": 172,
                  "pos": "IN",
                  "ner": "O",
                  "speaker": "PER0",
                  "before": " ",
                  "after": " "
                }
              },
              "IN"
            ],
            [
              {
                "nlpToken": {
                  "index": 12,
                  "word": "working",
                  "originalText": "working",
                  "lemma": "work",
                  "characterOffsetBegin": 173,
                  "characterOffsetEnd": 180,
                  "pos": "VBG",
                  "ner": "O",
                  "speaker": "PER0",
                  "before": " ",
                  "after": " "
                }
              },
              "VBG"
            ],
            [
              {
                "nlpToken": {
                  "index": 13,
                  "word": "with",
                  "originalText": "with",
                  "lemma": "with",
                  "characterOffsetBegin": 181,
                  "characterOffsetEnd": 185,
                  "pos": "IN",
                  "ner": "O",
                  "speaker": "PER0",
                  "before": " ",
                  "after": " "
                }
              },
              "IN"
            ],
            [
              {
                "nlpToken": {
                  "index": 14,
                  "word": "his",
                  "originalText": "his",
                  "lemma": "he",
                  "characterOffsetBegin": 186,
                  "characterOffsetEnd": 189,
                  "pos": "PRP$",
                  "ner": "O",
                  "speaker": "PER0",
                  "before": " ",
                  "after": " "
                }
              },
              "PRP$"
            ],
            [
              {
                "nlpToken": {
                  "index": 15,
                  "word": "father",
                  "originalText": "father",
                  "lemma": "father",
                  "characterOffsetBegin": 190,
                  "characterOffsetEnd": 196,
                  "pos": "NN",
                  "ner": "O",
                  "speaker": "PER0",
                  "before": " ",
                  "after": " "
                }
              },
              "NN"
            ],
            [
              {
                "nlpToken": {
                  "index": 16,
                  "word": "in",
                  "originalText": "in",
                  "lemma": "in",
                  "characterOffsetBegin": 197,
                  "characterOffsetEnd": 199,
                  "pos": "IN",
                  "ner": "O",
                  "speaker": "PER0",
                  "before": " ",
                  "after": " "
                }
              },
              "IN"
            ],
            [
              {
                "nlpToken": {
                  "index": 17,
                  "word": "a",
                  "originalText": "a",
                  "lemma": "a",
                  "characterOffsetBegin": 200,
                  "characterOffsetEnd": 201,
                  "pos": "DT",
                  "ner": "O",
                  "speaker": "PER0",
                  "before": " ",
                  "after": " "
                }
              },
              "DT"
            ],
            [
              {
                "nlpToken": {
                  "index": 18,
                  "word": "village",
                  "originalText": "village",
                  "lemma": "village",
                  "characterOffsetBegin": 202,
                  "characterOffsetEnd": 209,
                  "pos": "NN",
                  "ner": "O",
                  "speaker": "PER0",
                  "before": " ",
                  "after": " "
                }
              },
              "NN"
            ]
          ],
          "score": 1.0,
          "text": "fell into the 12-inch-wide well by accident while working with his father in a village",
          "nlpIndexSentence": 1
        }
      ],
      "label": "what"
    },
    "how": {
      "extracted": [
        {
          "parts": [
            [
              {
                "nlpToken": {
                  "index": 13,
                  "word": "a",
                  "originalText": "a",
                  "lemma": "a",
                  "characterOffsetBegin": 71,
                  "characterOffsetEnd": 72,
                  "pos": "DT",
                  "ner": "O",
                  "speaker": "PER0",
                  "before": " ",
                  "after": " "
                }
              },
              "DT"
            ],
            [
              {
                "nlpToken": {
                  "index": 14,
                  "word": "well",
                  "originalText": "well",
                  "lemma": "well",
                  "characterOffsetBegin": 73,
                  "characterOffsetEnd": 77,
                  "pos": "RB",
                  "ner": "O",
                  "speaker": "PER0",
                  "before": " ",
                  "after": " "
                }
              },
              "RB"
            ],
            [
              {
                "nlpToken": {
                  "index": 15,
                  "word": "on",
                  "originalText": "on",
                  "lemma": "on",
                  "characterOffsetBegin": 78,
                  "characterOffsetEnd": 80,
                  "pos": "IN",
                  "ner": "O",
                  "speaker": "PER0",
                  "before": " ",
                  "after": " "
                }
              },
              "IN"
            ],
            [
              {
                "nlpToken": {
                  "index": 16,
                  "word": "a",
                  "originalText": "a",
                  "lemma": "a",
                  "characterOffsetBegin": 81,
                  "characterOffsetEnd": 82,
                  "pos": "DT",
                  "ner": "O",
                  "speaker": "PER0",
                  "before": " ",
                  "after": " "
                }
              },
              "DT"
            ],
            [
              {
                "nlpToken": {
                  "index": 17,
                  "word": "Chinese",
                  "originalText": "Chinese",
                  "lemma": "chinese",
                  "characterOffsetBegin": 83,
                  "characterOffsetEnd": 90,
                  "pos": "JJ",
                  "ner": "MISC",
                  "speaker": "PER0",
                  "before": " ",
                  "after": " "
                },
                "aida": [
                  {
                    "mention": {
                      "allEntities": [
                        {
                          "kbIdentifier": "YAGO:China",
                          "disambiguationScore": "0.2613"
                        }
                      ],
                      "offset": 83,
                      "name": "Chinese",
                      "length": 7,
                      "bestEntity": {
                        "kbIdentifier": "YAGO:China",
                        "disambiguationScore": "0.2613"
                      }
                    },
                    "bestEntityMetadata": {
                      "knowledgebase": "YAGO",
                      "depictionurl": "http://upload.wikimedia.org/wikipedia/commons/f/fa/Flag_of_the_People%27s_Republic_of_China.svg",
                      "depictionthumbnailurl": "http://upload.wikimedia.org/wikipedia/commons/thumbFlag_of_the_People%27s_Republic_of_China.svg/200px-Flag_of_the_People%27s_Republic_of_China.svg",
                      "importance": 9.192157028782871e-06,
                      "entityId": "China",
                      "type": [
                        "YAGO_wordnet_system_108435388",
                        "YAGO_wordnet_district_108552138",
                        "YAGO_wikicategory_East_Asian_countries",
                        "YAGO_yagoPermanentlyLocatedEntity",
                        "YAGO_yagoLegalActorGeo",
                        "YAGO_wordnet_state_108654360",
                        "YAGO_wordnet_country_108544813",
                        "YAGO_wikicategory_Member_states_of_the_United_Nations",
                        "YAGO_wordnet_economy_108366753",
                        "YAGO_wikicategory_States_and_territories_established_in_1949",
                        "YAGO_wikicategory_Communist_states",
                        "YAGO_wordnet_abstraction_100002137",
                        "YAGO_wordnet_region_108630985",
                        "YAGO_yagoGeoEntity",
                        "YAGO_wordnet_physical_entity_100001930",
                        "YAGO_wikicategory_Central_Asian_countries",
                        "YAGO_wordnet_entity_100001740",
                        "YAGO_wikicategory_Single\\u002dparty_states",
                        "YAGO_wordnet_object_100002684",
                        "YAGO_wordnet_group_100031264",
                        "YAGO_wordnet_location_100027167",
                        "YAGO_wordnet_administrative_district_108491826",
                        "YAGO_wikicategory_Chinese\\u002dspeaking_countries_and_territories"
                      ],
                      "readableRepr": "China",
                      "url": "http://en.wikipedia.org/wiki/China"
                    }
                  }
                ]
              },
              "JJ"
            ],
            [
              {
                "nlpToken": {
                  "index": 18,
                  "word": "farm",
                  "originalText": "farm",
                  "lemma": "farm",
                  "characterOffsetBegin": 91,
                  "characterOffsetEnd": 95,
                  "pos": "NN",
                  "ner": "O",
                  "speaker": "PER0",
                  "before": " ",
                  "after": ""
                }
              },
              "NN"
            ],
            [
              {
                "nlpToken": {
                  "index": 19,
                  "word": ".",
                  "originalText": ".",
                  "lemma": ".",
                  "characterOffsetBegin": 95,
                  "characterOffsetEnd": 96,
                  "pos": ".",
                  "ner": "O",
                  "speaker": "PER0",
                  "before": "",
                  "after": " "
                }
              },
              "."
            ]
          ],
          "score": 1.0,
          "text": "a well on a Chinese farm ."
        }
      ],
      "label": "how"
    },
    "why": {
      "extracted": [
        {
          "parts": [
            [
              {
                "nlpToken": {
                  "index": 1,
                  "word": "Five-year-old",
                  "originalText": "Five-year-old",
                  "lemma": "five-year-old",
                  "characterOffsetBegin": 97,
                  "characterOffsetEnd": 110,
                  "pos": "JJ",
                  "ner": "DURATION",
                  "normalizedNER": "P5Y",
                  "speaker": "PER0",
                  "before": " ",
                  "after": " ",
                  "timex": {
                    "tid": "t1",
                    "type": "DURATION",
                    "value": "P5Y"
                  }
                }
              },
              "JJ"
            ],
            [
              {
                "nlpToken": {
                  "index": 2,
                  "word": "Zhao",
                  "originalText": "Zhao",
                  "lemma": "Zhao",
                  "characterOffsetBegin": 111,
                  "characterOffsetEnd": 115,
                  "pos": "NNP",
                  "ner": "PERSON",
                  "speaker": "PER0",
                  "before": " ",
                  "after": " "
                },
                "aida": [
                  {
                    "mention": {
                      "allEntities": [],
                      "offset": 111,
                      "name": "Zhao Zicong",
                      "length": 11
                    },
                    "bestEntityMetadata": null
                  }
                ]
              },
              "NNP"
            ],
            [
              {
                "nlpToken": {
                  "index": 3,
                  "word": "Zicong",
                  "originalText": "Zicong",
                  "lemma": "Zicong",
                  "characterOffsetBegin": 116,
                  "characterOffsetEnd": 122,
                  "pos": "NNP",
                  "ner": "PERSON",
                  "speaker": "PER0",
                  "before": " ",
                  "after": " "
                },
                "aida": [
                  {
                    "mention": {
                      "allEntities": [],
                      "offset": 111,
                      "name": "Zhao Zicong",
                      "length": 11
                    },
                    "bestEntityMetadata": null
                  }
                ]
              },
              "NNP"
            ]
          ],
          "score": 0.5565263157894738,
          "text": "Five-year-old Zhao Zicong",
          "nlpIndexSentence": 1
        }
      ],
      "label": "why"
    }
  },
  "fiveWoneH_Metadata": {
    "process_errors": {}
  }
}