{
  "authors": [
    "David Moye"
  ],
  "date_download": "2018-01-01T22:41:23",
  "date_modify": null,
  "date_publish": "2017-12-27T03:49:24",
  "description": "'My eyes just about popped out of my head'.",
  "filename": "http%3A%2F%2Fwww.huffingtonpost.com.au%2F2017%2F12%2F26%2Famerican-woman-receives-284-billion-electric-bill_a_23317450%2F%3Futm_hp_ref%3Dau-homepage.json",
  "image_url": "https://o.aolcdn.com/images/dims3/GLOB/crop/1200x630+0+0/resize/1200x630!/format/jpg/quality/85/http%3A%2F%2Fimg.huffingtonpost.com%2Fasset%2F1200_630%2F5a427a331c0000220068d47e.jpeg",
  "language": null,
  "localpath": null,
  "source_domain": "www.huffingtonpost.com.au",
  "text": "You can\u2019t blame Mary Horomanski for getting a little charged up when she saw her electric bill earlier this month.\nWhen the Erie, Pennsylvania, resident checked how much she owed the electric company online, she was met with a bill for a whopping $284 billion.\nYeah, you read that right.\n\u201cMy eyes just about popped out of my head,\u201d the 58-year-old Horomanski told the Erie Times-News. \u201cWe had put up Christmas lights and I wondered if we had put them up wrong.\u201d\nOn the bright side, she had a full year to pay the entire $284 billion. Her minimum payment would be a mere $28,156, according to The Associated Press.\nFor some reason, Horomanski suspected there might have been a billing error, which was confirmed when her son called electricity provider Penelec.\nTurns out, she only owed $284.46 \u2015 still high, but much more manageable.\nMark Durbin, a spokesman for Penelec\u2019s parent company First Energy, said he has never seen a bill for billions of dollars, but told the Erie Times-News the company appreciates Horomanski\u2019s \u201dwillingness to reach out to us about the mistake.\u201d\nThe multibillion-dollar bill did inspire Horomanski to add an item to her Christmas list.\n\u201cI told [my son] I want a heart monitor,\u201d she told the paper.\nAccidentally high bills are a shocking part of modern life.\nIn August 2012, a British woman on vacation in South Wales bought a cheap mobile phone because her own cell couldn\u2019t pick up the local signal.\nThanks to a technical glitch, she ended up being slapped with a bill for more than $42,000.\nIn July 2012, a bank error caused a Nashville, Tennessee, man to be charged $84,522.54 for a $30 tank of gas.\nGood thing he saved the receipt.",
  "title": "American Woman Receives $284 BILLION Electric Bill",
  "title_page": null,
  "title_rss": null,
  "url": "http://www.huffingtonpost.com.au/2017/12/26/american-woman-receives-284-billion-electric-bill_a_23317450/?utm_hp_ref=au-homepage",
  "newsCluster": {
    "CategoryId": 2,
    "Category": "business",
    "TopicId": 1,
    "Topic": "unspecific",
    "EventId": 5,
    "Event": "woman_gets_284_billion_electric_bil",
    "Url": "http://www.huffingtonpost.com.au/2017/12/26/american-woman-receives-284-billion-electric-bill_a_23317450/?utm_hp_ref=au-homepage"
  },
  "dId": "c7805f712f073962ef80e9266d73fc89ccdebd41382f51303b6711e3",
  "fiveWoneH": {
    "how": {
      "extracted": [
        {
          "parts": [
            [
              {
                "nlpToken": {
                  "index": 2,
                  "word": "some",
                  "originalText": "some",
                  "lemma": "some",
                  "characterOffsetBegin": 715,
                  "characterOffsetEnd": 719,
                  "pos": "DT",
                  "ner": "O",
                  "speaker": "PER0",
                  "before": " ",
                  "after": " "
                }
              },
              "DT"
            ],
            [
              {
                "nlpToken": {
                  "index": 3,
                  "word": "reason",
                  "originalText": "reason",
                  "lemma": "reason",
                  "characterOffsetBegin": 720,
                  "characterOffsetEnd": 726,
                  "pos": "NN",
                  "ner": "O",
                  "speaker": "PER0",
                  "before": " ",
                  "after": ""
                }
              },
              "NN"
            ],
            [
              {
                "nlpToken": {
                  "index": 4,
                  "word": ",",
                  "originalText": ",",
                  "lemma": ",",
                  "characterOffsetBegin": 726,
                  "characterOffsetEnd": 727,
                  "pos": ",",
                  "ner": "O",
                  "speaker": "PER0",
                  "before": "",
                  "after": " "
                }
              },
              ","
            ],
            [
              {
                "nlpToken": {
                  "index": 5,
                  "word": "Horomanski",
                  "originalText": "Horomanski",
                  "lemma": "Horomanski",
                  "characterOffsetBegin": 728,
                  "characterOffsetEnd": 738,
                  "pos": "NNP",
                  "ner": "PERSON",
                  "speaker": "PER0",
                  "before": " ",
                  "after": " "
                }
              },
              "NNP"
            ]
          ],
          "score": 1.0,
          "text": "some reason , Horomanski",
          "nlpIndexSentence": 2
        }
      ],
      "label": "how"
    },
    "who": {
      "extracted": [
        {
          "parts": [
            [
              {
                "nlpToken": {
                  "index": 15,
                  "word": "Horomanski",
                  "originalText": "Horomanski",
                  "lemma": "Horomanski",
                  "characterOffsetBegin": 445,
                  "characterOffsetEnd": 455,
                  "pos": "NNP",
                  "ner": "PERSON",
                  "speaker": "PER0",
                  "before": " ",
                  "after": " "
                }
              },
              "NNP"
            ]
          ],
          "score": 1.0,
          "text": "Horomanski",
          "nlpIndexSentence": 3
        }
      ],
      "label": "who"
    },
    "what": {
      "extracted": [
        {
          "parts": [
            [
              {
                "nlpToken": {
                  "index": 15,
                  "word": "saw",
                  "originalText": "saw",
                  "lemma": "see",
                  "characterOffsetBegin": 170,
                  "characterOffsetEnd": 173,
                  "pos": "VBD",
                  "ner": "O",
                  "speaker": "PER0",
                  "before": " ",
                  "after": " "
                }
              },
              "VBD"
            ],
            [
              {
                "nlpToken": {
                  "index": 16,
                  "word": "her",
                  "originalText": "her",
                  "lemma": "she",
                  "characterOffsetBegin": 174,
                  "characterOffsetEnd": 177,
                  "pos": "PRP$",
                  "ner": "O",
                  "speaker": "PER0",
                  "before": " ",
                  "after": " "
                }
              },
              "PRP$"
            ],
            [
              {
                "nlpToken": {
                  "index": 17,
                  "word": "electric",
                  "originalText": "electric",
                  "lemma": "electric",
                  "characterOffsetBegin": 178,
                  "characterOffsetEnd": 186,
                  "pos": "JJ",
                  "ner": "O",
                  "speaker": "PER0",
                  "before": " ",
                  "after": " "
                }
              },
              "JJ"
            ],
            [
              {
                "nlpToken": {
                  "index": 18,
                  "word": "bill",
                  "originalText": "bill",
                  "lemma": "bill",
                  "characterOffsetBegin": 187,
                  "characterOffsetEnd": 191,
                  "pos": "NN",
                  "ner": "O",
                  "speaker": "PER0",
                  "before": " ",
                  "after": " "
                }
              },
              "NN"
            ]
          ],
          "score": 1.0,
          "text": "saw her electric bill",
          "nlpIndexSentence": 3
        }
      ],
      "label": "what"
    },
    "why": {
      "extracted": [
        {
          "parts": [
            [
              {
                "nlpToken": {
                  "index": 17,
                  "word": "phone",
                  "originalText": "phone",
                  "lemma": "phone",
                  "characterOffsetBegin": 1465,
                  "characterOffsetEnd": 1470,
                  "pos": "NN",
                  "ner": "O",
                  "speaker": "PER0",
                  "before": " ",
                  "after": " "
                }
              },
              "NN"
            ],
            [
              {
                "nlpToken": {
                  "index": 18,
                  "word": "because",
                  "originalText": "because",
                  "lemma": "because",
                  "characterOffsetBegin": 1471,
                  "characterOffsetEnd": 1478,
                  "pos": "IN",
                  "ner": "O",
                  "speaker": "PER0",
                  "before": " ",
                  "after": " "
                }
              },
              "IN"
            ],
            [
              {
                "nlpToken": {
                  "index": 19,
                  "word": "her",
                  "originalText": "her",
                  "lemma": "she",
                  "characterOffsetBegin": 1479,
                  "characterOffsetEnd": 1482,
                  "pos": "PRP$",
                  "ner": "O",
                  "speaker": "PER0",
                  "before": " ",
                  "after": " "
                }
              },
              "PRP$"
            ],
            [
              {
                "nlpToken": {
                  "index": 20,
                  "word": "own",
                  "originalText": "own",
                  "lemma": "own",
                  "characterOffsetBegin": 1483,
                  "characterOffsetEnd": 1486,
                  "pos": "JJ",
                  "ner": "O",
                  "speaker": "PER0",
                  "before": " ",
                  "after": " "
                }
              },
              "JJ"
            ],
            [
              {
                "nlpToken": {
                  "index": 21,
                  "word": "cell",
                  "originalText": "cell",
                  "lemma": "cell",
                  "characterOffsetBegin": 1487,
                  "characterOffsetEnd": 1491,
                  "pos": "NN",
                  "ner": "O",
                  "speaker": "PER0",
                  "before": " ",
                  "after": " "
                }
              },
              "NN"
            ],
            [
              {
                "nlpToken": {
                  "index": 22,
                  "word": "could",
                  "originalText": "could",
                  "lemma": "could",
                  "characterOffsetBegin": 1492,
                  "characterOffsetEnd": 1497,
                  "pos": "MD",
                  "ner": "O",
                  "speaker": "PER0",
                  "before": " ",
                  "after": ""
                }
              },
              "MD"
            ],
            [
              {
                "nlpToken": {
                  "index": 23,
                  "word": "n't",
                  "originalText": "n\u2019t",
                  "lemma": "not",
                  "characterOffsetBegin": 1497,
                  "characterOffsetEnd": 1500,
                  "pos": "RB",
                  "ner": "O",
                  "speaker": "PER0",
                  "before": "",
                  "after": " "
                }
              },
              "RB"
            ],
            [
              {
                "nlpToken": {
                  "index": 24,
                  "word": "pick",
                  "originalText": "pick",
                  "lemma": "pick",
                  "characterOffsetBegin": 1501,
                  "characterOffsetEnd": 1505,
                  "pos": "VB",
                  "ner": "O",
                  "speaker": "PER0",
                  "before": " ",
                  "after": " "
                }
              },
              "VB"
            ],
            [
              {
                "nlpToken": {
                  "index": 25,
                  "word": "up",
                  "originalText": "up",
                  "lemma": "up",
                  "characterOffsetBegin": 1506,
                  "characterOffsetEnd": 1508,
                  "pos": "RP",
                  "ner": "O",
                  "speaker": "PER0",
                  "before": " ",
                  "after": " "
                }
              },
              "RP"
            ],
            [
              {
                "nlpToken": {
                  "index": 26,
                  "word": "the",
                  "originalText": "the",
                  "lemma": "the",
                  "characterOffsetBegin": 1509,
                  "characterOffsetEnd": 1512,
                  "pos": "DT",
                  "ner": "O",
                  "speaker": "PER0",
                  "before": " ",
                  "after": " "
                }
              },
              "DT"
            ],
            [
              {
                "nlpToken": {
                  "index": 27,
                  "word": "local",
                  "originalText": "local",
                  "lemma": "local",
                  "characterOffsetBegin": 1513,
                  "characterOffsetEnd": 1518,
                  "pos": "JJ",
                  "ner": "O",
                  "speaker": "PER0",
                  "before": " ",
                  "after": " "
                }
              },
              "JJ"
            ],
            [
              {
                "nlpToken": {
                  "index": 28,
                  "word": "signal",
                  "originalText": "signal",
                  "lemma": "signal",
                  "characterOffsetBegin": 1519,
                  "characterOffsetEnd": 1525,
                  "pos": "NN",
                  "ner": "O",
                  "speaker": "PER0",
                  "before": " ",
                  "after": ""
                }
              },
              "NN"
            ],
            [
              {
                "nlpToken": {
                  "index": 29,
                  "word": ".",
                  "originalText": ".",
                  "lemma": ".",
                  "characterOffsetBegin": 1525,
                  "characterOffsetEnd": 1526,
                  "pos": ".",
                  "ner": "O",
                  "speaker": "PER0",
                  "before": "",
                  "after": "\n"
                }
              },
              "."
            ]
          ],
          "score": 0.6639999999999999,
          "text": "phone because her own cell could n\u2019t pick up the local signal .",
          "nlpIndexSentence": 16
        }
      ],
      "label": "why"
    },
    "where": {
      "extracted": [
        {
          "parts": [
            [
              {
                "nlpToken": {
                  "index": 5,
                  "word": "Pennsylvania",
                  "originalText": "Pennsylvania",
                  "lemma": "Pennsylvania",
                  "characterOffsetBegin": 227,
                  "characterOffsetEnd": 239,
                  "pos": "NNP",
                  "ner": "LOCATION",
                  "speaker": "PER0",
                  "before": " ",
                  "after": ""
                }
              },
              "NNP"
            ]
          ],
          "score": 0.91,
          "text": "Pennsylvania",
          "enhancement": {
            "openstreetmap_nominatim": {
              "place_id": "179769986",
              "licence": "Data \u00a9 OpenStreetMap contributors, ODbL 1.0. http://www.openstreetmap.org/copyright",
              "osm_type": "relation",
              "osm_id": "162109",
              "boundingbox": [
                39.7197662,
                42.5146891,
                -80.5210833,
                -74.689502
              ],
              "lat": "40.9699889",
              "lon": "-77.7278831",
              "display_name": "Pennsylvania, United States of America",
              "class": "boundary",
              "type": "administrative",
              "importance": 0.30642406050544,
              "icon": "https://nominatim.openstreetmap.org/images/mapicons/poi_boundary_administrative.p.20.png"
            }
          },
          "nlpIndexSentence": 4
        }
      ],
      "label": "where"
    },
    "when": {
      "extracted": [
        {
          "parts": [
            [
              {
                "nlpToken": {
                  "index": 13,
                  "word": "Christmas",
                  "originalText": "Christmas",
                  "lemma": "Christmas",
                  "characterOffsetBegin": 1246,
                  "characterOffsetEnd": 1255,
                  "pos": "NNP",
                  "ner": "DATE",
                  "normalizedNER": "2017-12-25",
                  "speaker": "PER0",
                  "before": " ",
                  "after": " ",
                  "timex": {
                    "tid": "t5",
                    "type": "DATE",
                    "value": "2017-12-25"
                  }
                }
              },
              "NNP"
            ]
          ],
          "score": 0.5775929194771179,
          "text": "Christmas",
          "enhancement": {
            "timex": {
              "start_date": "2017-12-25T00:00:00",
              "end_date": "2017-12-25T23:59:59"
            }
          },
          "nlpIndexSentence": 13
        }
      ],
      "label": "when"
    }
  }
}