{
  "_version": "1.1.0",
  "resources": [
    {
      "name": ".theming",
      "theme": "sap_hcb"
    },
    {
      "name": "BrowserScrollbar.less",
      "designtime": true,
      "theme": "sap_hcb"
    },
    {
      "name": "Icon.less",
      "designtime": true,
      "theme": "sap_hcb"
    },
    {
      "name": "LocalBusyIndicator.less",
      "designtime": true,
      "theme": "sap_hcb"
    },
    {
      "name": "Shadow.less",
      "designtime": true,
      "theme": "sap_hcb"
    },
    {
      "name": "global.less",
      "designtime": true,
      "theme": "sap_hcb"
    },
    {
      "name": "img-RTL/message/16x16/Message_Icon_Error.png",
      "theme": "sap_hcb"
    },
    {
      "name": "img-RTL/message/16x16/Message_Icon_Information.png",
      "theme": "sap_hcb"
    },
    {
      "name": "img-RTL/message/16x16/Message_Icon_Success.png",
      "theme": "sap_hcb"
    },
    {
      "name": "img-RTL/message/16x16/Message_Icon_Warning.png",
      "theme": "sap_hcb"
    },
    {
      "name": "img-RTL/message/32x32/Message_Icon_Error.png",
      "theme": "sap_hcb"
    },
    {
      "name": "img-RTL/message/32x32/Message_Icon_Information.png",
      "theme": "sap_hcb"
    },
    {
      "name": "img-RTL/message/32x32/Message_Icon_Success.png",
      "theme": "sap_hcb"
    },
    {
      "name": "img-RTL/message/32x32/Message_Icon_Warning.png",
      "theme": "sap_hcb"
    },
    {
      "name": "img/message/16x16/Message_Icon_Error.png",
      "theme": "sap_hcb"
    },
    {
      "name": "img/message/16x16/Message_Icon_Information.png",
      "theme": "sap_hcb"
    },
    {
      "name": "img/message/16x16/Message_Icon_Success.png",
      "theme": "sap_hcb"
    },
    {
      "name": "img/message/16x16/Message_Icon_Warning.png",
      "theme": "sap_hcb"
    },
    {
      "name": "img/message/32x32/Message_Icon_Error.png",
      "theme": "sap_hcb"
    },
    {
      "name": "img/message/32x32/Message_Icon_Information.png",
      "theme": "sap_hcb"
    },
    {
      "name": "img/message/32x32/Message_Icon_Success.png",
      "theme": "sap_hcb"
    },
    {
      "name": "img/message/32x32/Message_Icon_Warning.png",
      "theme": "sap_hcb"
    },
    {
      "name": "library-RTL-dbg.css",
      "isDebug": true,
      "theme": "sap_hcb"
    },
    {
      "name": "library-RTL.css",
      "theme": "sap_hcb"
    },
    {
      "name": "library-dbg.css",
      "isDebug": true,
      "theme": "sap_hcb"
    },
    {
      "name": "library-parameters.json",
      "theme": "sap_hcb"
    },
    {
      "name": "library.css",
      "theme": "sap_hcb"
    },
    {
      "name": "library.less",
      "designtime": true,
      "theme": "sap_hcb"
    },
    {
      "name": "library.source.less",
      "designtime": true,
      "theme": "sap_hcb"
    },
    {
      "name": "shared.less",
      "designtime": true,
      "theme": "sap_hcb"
    }
  ]
}